nonebot_plugin_wakatime-0.3.0.dist-info/METADATA
nonebot_plugin_wakatime-0.3.0.dist-info/WHEEL
nonebot_plugin_wakatime-0.3.0.dist-info/entry_points.txt
nonebot_plugin_wakatime-0.3.0.dist-info/licenses/LICENSE
nonebot_plugin_wakatime/__init__.py
nonebot_plugin_wakatime/apis/__init__.py
nonebot_plugin_wakatime/apis/request.py
nonebot_plugin_wakatime/bootstrap.py
nonebot_plugin_wakatime/config.py
nonebot_plugin_wakatime/exception.py
nonebot_plugin_wakatime/migrations/263d60026863_adapt_user_plugin.py
nonebot_plugin_wakatime/migrations/2e39fdc3f6b1_add_length_in_varchar.py
nonebot_plugin_wakatime/migrations/__init__.py
nonebot_plugin_wakatime/migrations/a27298ba954d_first_revision.py
nonebot_plugin_wakatime/migrations/e4cefad24e6c_add_subscription_table.py
nonebot_plugin_wakatime/models.py
nonebot_plugin_wakatime/mount.py
nonebot_plugin_wakatime/render_pic.py
nonebot_plugin_wakatime/resources/fonts/NotoColorEmoji-Regular.ttf
nonebot_plugin_wakatime/resources/images/background.png
nonebot_plugin_wakatime/resources/images/default_avatar.jpg
nonebot_plugin_wakatime/resources/templates/error.html.jinja2
nonebot_plugin_wakatime/resources/templates/icons.macros.html.jinja2
nonebot_plugin_wakatime/resources/templates/index.css
nonebot_plugin_wakatime/resources/templates/profile.html.jinja2
nonebot_plugin_wakatime/resources/templates/subscription.html.jinja2
nonebot_plugin_wakatime/resources/templates/success.html.jinja2
nonebot_plugin_wakatime/schedule.py
nonebot_plugin_wakatime/schema/__init__.py
nonebot_plugin_wakatime/schema/stats.py
nonebot_plugin_wakatime/schema/users.py
nonebot_plugin_wakatime/utils.py
nonebot_plugin_wakatime-0.3.0.dist-info/RECORD
