Metadata-Version: 2.1
Name: nonebot-plugin-wakatime
Version: 0.3.0
Summary: 将代码统计嵌入 Bot 中
Author-Email: KomoriDev <mute231010@gmail.com>
License: MIT
Requires-Python: >=3.10
Requires-Dist: nonebot2>=2.3.2
Requires-Dist: nonebot-plugin-alconna>=0.49.0
Requires-Dist: nonebot-plugin-orm>=0.7.4
Requires-Dist: nonebot-plugin-session>=0.3.1
Requires-Dist: nonebot-plugin-htmlrender>=0.3.3
Requires-Dist: nonebot-plugin-user>=0.3.0
Requires-Dist: nonebot-plugin-localstore>=0.7.1
Requires-Dist: expiringdictx>=1.0.1
Requires-Dist: httpx>=0.27.0
Requires-Dist: nonebot-plugin-argot>=0.1.6
Provides-Extra: adapters
Requires-Dist: nonebot-adapter-onebot>=2.4.4; extra == "adapters"
Requires-Dist: nonebot-adapter-telegram>=0.1.0b17; extra == "adapters"
Provides-Extra: tests
Requires-Dist: viztracer>=0.16.3; extra == "tests"
Requires-Dist: pytest>=8.3.2; extra == "tests"
Requires-Dist: pytest-asyncio>=0.23.8; extra == "tests"
Requires-Dist: pytest-cov>=5.0.0; extra == "tests"
Requires-Dist: nonebug>=0.3.7; extra == "tests"
Requires-Dist: asyncpg>=0.29.0; extra == "tests"
Requires-Dist: aiomysql>=0.2.0; extra == "tests"
Requires-Dist: nb-cli>=1.4.1; extra == "tests"
Requires-Dist: cryptography>=43.0.0; extra == "tests"
Requires-Dist: pytest-mock>=3.14.0; extra == "tests"
Requires-Dist: respx>=0.21.1; extra == "tests"
Provides-Extra: extra
Requires-Dist: nonebot2[fastapi]>=2.3.2; extra == "extra"
Requires-Dist: nonebot-plugin-orm[aiosqlite]>=0.7.5; extra == "extra"
Provides-Extra: apscheduler
Requires-Dist: nonebot-plugin-apscheduler>=0.5.0; extra == "apscheduler"
